README.md
setup.py
PythonGoogleSpreadsheet/PythonGoogleSpreadsheet.py
PythonGoogleSpreadsheet/__init__.py
PythonGoogleSpreadsheet.egg-info/PKG-INFO
PythonGoogleSpreadsheet.egg-info/SOURCES.txt
PythonGoogleSpreadsheet.egg-info/dependency_links.txt
PythonGoogleSpreadsheet.egg-info/requires.txt
PythonGoogleSpreadsheet.egg-info/top_level.txt