Metadata-Version: 1.1
Name: PythonGoogleSpreadsheet
Version: 0.4.5
Summary: Simple wrapper to create Google Spreadsheet, using Python 3+"
Home-page: https://github.com/HolmesInc/PythonGoogleSpreadsheet
Author: Andrew Babenko
Author-email: andruonline11@gmail.com
License: LICENSE
Platform: UNKNOWN
Classifier: Intended Audience :: Developers
Classifier: Programming Language :: Python
Classifier: License :: OSI Approved :: Apache Software License
Classifier: Operating System :: OS Independent
Classifier: Topic :: Software Development
Classifier: Topic :: Software Development :: Libraries :: Python Modules
Classifier: Topic :: Office/Business :: Financial :: Spreadsheet
